koya_quality/__init__.py
koya_quality/koya_quality.py
koya_quality-0.0.5.dist-info/LICENSE
koya_quality-0.0.5.dist-info/METADATA
koya_quality-0.0.5.dist-info/WHEEL
koya_quality-0.0.5.dist-info/top_level.txt
koya_quality-0.0.5.dist-info/RECORD
