Metadata-Version: 2.1
Name: koya-quality
Version: 0.0.5
Author: 
Author-email: 
License: MIT
Requires-Python: >=3.6
License-File: LICENSE
Requires-Dist: pandas
Requires-Dist: koya-python-airtable
Requires-Dist: koya-utilities
Requires-Dist: boto3
